adafruit_bmp3xx.py
adafruit_circuitpython_bmp3xx-1.3.25.dist-info/licenses/LICENSE
adafruit_circuitpython_bmp3xx-1.3.25.dist-info/METADATA
adafruit_circuitpython_bmp3xx-1.3.25.dist-info/WHEEL
adafruit_circuitpython_bmp3xx-1.3.25.dist-info/top_level.txt
adafruit_circuitpython_bmp3xx-1.3.25.dist-info/RECORD
