Metadata-Version: 2.4
Name: adafruit-circuitpython-bmp3xx
Version: 1.3.25
Summary: CircuitPython library for BMP3XX Temperature and Barometric Pressure sensor.
Author-email: Adafruit Industries <circuitpython@adafruit.com>
License: MIT
Project-URL: Homepage, https://github.com/adafruit/Adafruit_CircuitPython_BMP3XX
Keywords: adafruit,temperature,barometric,pressure,temp,bmp3xx,bmp388,hardware,micropython,circuitpython
Classifier: Intended Audience :: Developers
Classifier: Topic :: Software Development :: Libraries
Classifier: Topic :: Software Development :: Embedded Systems
Classifier: Topic :: System :: Hardware
Classifier: License :: OSI Approved :: MIT License
Classifier: Programming Language :: Python :: 3
License-File: LICENSE
Requires-Dist: Adafruit-Blinka
Requires-Dist: adafruit-circuitpython-busdevice
Provides-Extra: optional
Dynamic: license-file
